LICENSE
MANIFEST.in
README.md
logo.png
requirements.txt
setup.cfg
setup.py
mosqito/__init__.py
mosqito.egg-info/PKG-INFO
mosqito.egg-info/SOURCES.txt
mosqito.egg-info/dependency_links.txt
mosqito.egg-info/requires.txt
mosqito.egg-info/top_level.txt
mosqito/sound_level_meter/__init__.py
mosqito/sound_level_meter/freq_band_synthesis.py
mosqito/sound_level_meter/spectrum.py
mosqito/sound_level_meter/noct_spectrum/__init__.py
mosqito/sound_level_meter/noct_spectrum/_center_freq.py
mosqito/sound_level_meter/noct_spectrum/_filter_bandwidth.py
mosqito/sound_level_meter/noct_spectrum/_getFrequencies.py
mosqito/sound_level_meter/noct_spectrum/_n_oct_freq_filter.py
mosqito/sound_level_meter/noct_spectrum/_n_oct_time_filter.py
mosqito/sound_level_meter/noct_spectrum/_nominal_frequency.py
mosqito/sound_level_meter/noct_spectrum/noct_spectrum.py
mosqito/sound_level_meter/noct_spectrum/noct_synthesis.py
mosqito/sq_metrics/__init__.py
mosqito/sq_metrics/loudness/__init__.py
mosqito/sq_metrics/loudness/loudness_ecma/__init__.py
mosqito/sq_metrics/loudness/loudness_ecma/_auditory_filters_centre_freq.py
mosqito/sq_metrics/loudness/loudness_ecma/_ear_filter_design.py
mosqito/sq_metrics/loudness/loudness_ecma/_gammatone.py
mosqito/sq_metrics/loudness/loudness_ecma/_loudness_ecma_data.py
mosqito/sq_metrics/loudness/loudness_ecma/_nonlinearity.py
mosqito/sq_metrics/loudness/loudness_ecma/_rectified_band_pass_signals.py
mosqito/sq_metrics/loudness/loudness_ecma/loudness_ecma.py
mosqito/sq_metrics/loudness/loudness_zwst/__init__.py
mosqito/sq_metrics/loudness/loudness_zwst/_calc_slopes.py
mosqito/sq_metrics/loudness/loudness_zwst/_get_rns_index.py
mosqito/sq_metrics/loudness/loudness_zwst/_main_loudness.py
mosqito/sq_metrics/loudness/loudness_zwst/loudness_zwst.py
mosqito/sq_metrics/loudness/loudness_zwst/loudness_zwst_freq.py
mosqito/sq_metrics/loudness/loudness_zwst/loudness_zwst_perseg.py
mosqito/sq_metrics/loudness/loudness_zwtv/__init__.py
mosqito/sq_metrics/loudness/loudness_zwtv/_lowpass_intp.py
mosqito/sq_metrics/loudness/loudness_zwtv/_nonlinear_decay.py
mosqito/sq_metrics/loudness/loudness_zwtv/_square_and_smooth.py
