Metadata-Version: 2.1
Name: mosqito
Version: 1.1.1
Summary: Modular Sound Quality Integrated Toolbox
Home-page: https://github.com/Eomys/MoSQITo
Download-URL: https://github.com/Eomys/MoSQITo/archive/v1.1.1.tar.gz
Author: MoSQITo Developers
Author-email: martin.glesser@eomys.com
Classifier: Programming Language :: Python :: 3
Classifier: License :: OSI Approved :: Apache Software License
Classifier: Operating System :: OS Independent
Requires-Python: >= 3.5
License-File: LICENSE
